genbase/__init__.py
genbase/_version.py
genbase/decorator.py
genbase/internationalization.py
genbase/mixin.py
genbase/utils.py
genbase/data/__init__.py
genbase/locale/__init__.py
genbase/locale/en.json
genbase/locale/nl.json
genbase/model/__init__.py
genbase/test/test_internationalization.py
genbase/ui/__init__.py
genbase/ui/notebook.py
genbase/ui/svg.py
genbase/ui/plot/__init__.py
genbase-0.3.6.dist-info/LICENSE
genbase-0.3.6.dist-info/METADATA
genbase-0.3.6.dist-info/WHEEL
genbase-0.3.6.dist-info/top_level.txt
genbase-0.3.6.dist-info/RECORD
