Metadata-Version: 2.1
Name: genbase
Version: 0.3.6
Summary: Generation base dependency
Home-page: https://git.science.uu.nl/m.j.robeer/genbase
Author: Marcel Robeer
Author-email: m.j.robeer@uu.nl
License: GNU LGPL v3
Platform: UNKNOWN
Classifier: Development Status :: 3 - Alpha
Classifier: Programming Language :: Python
Classifier: License :: OSI Approved :: GNU Lesser General Public License v3 or later (LGPLv3+)
Classifier: Topic :: Scientific/Engineering :: Artificial Intelligence
Requires-Python: >=3.8
License-File: LICENSE
Requires-Dist: instancelib (>=0.4.4.1)
Requires-Dist: instancelib-onnx (>=0.1.3)
Requires-Dist: matplotlib (>=3.5.0)
Requires-Dist: numpy (>=1.19.5)
Requires-Dist: python-i18n (>=0.3.9)
Requires-Dist: srsly (>=2.4.2)
Requires-Dist: requests
Requires-Dist: ipython (>=7.30.1)
Requires-Dist: lazy-load (>=0.8.2)
Requires-Dist: onnxruntime ; python_version < "3.10"
Requires-Dist: onnxruntime (>=1.12.0) ; python_version >= "3.10"
